tests/__init__.py
tests/conftest.py
tests/test_blockcerts.py
tests/test_helpers.py
verifiable_credentials/__init__.py
verifiable_credentials/components.py
verifiable_credentials/helpers.py
verifiable_credentials/issue.py
vcpy-0.0.2.dist-info/LICENSE
vcpy-0.0.2.dist-info/METADATA
vcpy-0.0.2.dist-info/WHEEL
vcpy-0.0.2.dist-info/top_level.txt
vcpy-0.0.2.dist-info/RECORD
