Metadata-Version: 2.1
Name: vcpy
Version: 0.0.2
Summary: Issue verifiable credentials with ease.
Home-page: https://github.com/docknetwork/vcpy
Author: Fausto Woelflin
Author-email: fausto@dock.io
License: UNKNOWN
Keywords: verifiable credentials blockcerts issuing blockchain certificates claims signed open badges
Platform: UNKNOWN
Classifier: Programming Language :: Python :: 3
Classifier: License :: OSI Approved :: MIT License
Classifier: Operating System :: OS Independent
Requires-Python: >=3.6
